README
runtime.py
setup.py
runtime.egg-info/PKG-INFO
runtime.egg-info/SOURCES.txt
runtime.egg-info/dependency_links.txt
runtime.egg-info/not-zip-safe
runtime.egg-info/top_level.txt