Metadata-Version: 1.0
Name: runtime
Version: 0.1.1
Summary: app runtime management
Home-page: UNKNOWN
Author: Andrey Popp
Author-email: 8mayday@gmail.com
License: UNKNOWN
Platform: UNKNOWN
